voyant_indicators/__init__.py
voyant_indicators/cli.py
voyant_indicators/voyant_indicators.py
voyant_indicators/experimental/__init__.py
voyant_indicators/experimental/kalman.py
voyant_indicators/momentum/__init__.py
voyant_indicators/momentum/ao.py
voyant_indicators/momentum/apo.py
voyant_indicators/momentum/mfi.py
voyant_indicators/momentum/mom.py
voyant_indicators/momentum/ppo.py
voyant_indicators/momentum/roc.py
voyant_indicators/momentum/rocr.py
voyant_indicators/momentum/rsi.py
voyant_indicators/momentum/stoch.py
voyant_indicators/momentum/stochf.py
voyant_indicators/momentum/ultosc.py
voyant_indicators/momentum/willr.py
voyant_indicators/overlapping_studies/__init__.py
voyant_indicators/overlapping_studies/dema.py
voyant_indicators/overlapping_studies/ema.py
voyant_indicators/overlapping_studies/kama.py
voyant_indicators/overlapping_studies/sma.py
voyant_indicators/overlapping_studies/tema.py
voyant_indicators/overlapping_studies/wma.py
voyant_indicators/price_action/__init__.py
voyant_indicators/price_action/ohlcv.py
voyant_indicators/price_action/prev_n.py
voyant_indicators/trend/__init__.py
voyant_indicators/trend/accelerator_oscillator.py
voyant_indicators/trend/adx.py
voyant_indicators/trend/aroon.py
voyant_indicators/trend/aroonosc.py
voyant_indicators/trend/bop.py
voyant_indicators/trend/cci.py
voyant_indicators/trend/dema.py
voyant_indicators/trend/demarker.py
voyant_indicators/trend/donchian_channel.py
voyant_indicators/trend/ema.py
voyant_indicators/trend/ichimoku.py
voyant_indicators/trend/kama.py
voyant_indicators/trend/macd.py
voyant_indicators/trend/macdext.py
voyant_indicators/trend/parabolic_sar.py
voyant_indicators/trend/sma.py
voyant_indicators/trend/supertrend.py
voyant_indicators/trend/t3.py
voyant_indicators/trend/tema.py
voyant_indicators/trend/trima.py
voyant_indicators/trend/trix.py
voyant_indicators/trend/vortex.py
voyant_indicators/trend/wma.py
voyant_indicators/util/__init__.py
voyant_indicators/util/midpnt.py
voyant_indicators-0.2.2.4.dist-info/AUTHORS.rst
voyant_indicators-0.2.2.4.dist-info/METADATA
voyant_indicators-0.2.2.4.dist-info/WHEEL
voyant_indicators-0.2.2.4.dist-info/entry_points.txt
voyant_indicators-0.2.2.4.dist-info/top_level.txt
voyant_indicators-0.2.2.4.dist-info/RECORD
