Metadata-Version: 2.1
Name: voyant-indicators
Version: 0.2.2.4
Summary: technical analysis indicators for voyant
Home-page: https://github.com/marmikcfc/voyant_indicators
Author: Marmik Pandya
Author-email: marmikapndya@gmail.com
License: UNKNOWN
Keywords: voyant_indicators
Platform: UNKNOWN
Classifier: Development Status :: 2 - Pre-Alpha
Classifier: Intended Audience :: Developers
Classifier: Natural Language :: English
Classifier: Programming Language :: Python :: 3
Classifier: Programming Language :: Python :: 3.5
Classifier: Programming Language :: Python :: 3.6
Classifier: Programming Language :: Python :: 3.7
Classifier: Programming Language :: Python :: 3.8
Requires-Python: >=3.5
Requires-Dist: Click (>=7.0)
Requires-Dist: numpy
Requires-Dist: pandas
Requires-Dist: pykalman
